odoo/addons/account_banking_mandate_sale/README.rst
odoo/addons/account_banking_mandate_sale/__init__.py
odoo/addons/account_banking_mandate_sale/__manifest__.py
odoo/addons/account_banking_mandate_sale/i18n/account_banking_mandate_sale.pot
odoo/addons/account_banking_mandate_sale/i18n/de.po
odoo/addons/account_banking_mandate_sale/i18n/es.po
odoo/addons/account_banking_mandate_sale/i18n/hr.po
odoo/addons/account_banking_mandate_sale/i18n/nl.po
odoo/addons/account_banking_mandate_sale/i18n/nl_NL.po
odoo/addons/account_banking_mandate_sale/i18n/pt_BR.po
odoo/addons/account_banking_mandate_sale/i18n/sl.po
odoo/addons/account_banking_mandate_sale/models/__init__.py
odoo/addons/account_banking_mandate_sale/models/sale_order.py
odoo/addons/account_banking_mandate_sale/static/description/icon.png
odoo/addons/account_banking_mandate_sale/views/sale_order.xml
odoo/addons/account_banking_mandate_sale/wizard/__init__.py
odoo/addons/account_banking_mandate_sale/wizard/sale_make_invoice_advance.py
odoo11_addon_account_banking_mandate_sale-11.0.1.0.0.99.dev3.dist-info/METADATA
odoo11_addon_account_banking_mandate_sale-11.0.1.0.0.99.dev3.dist-info/WHEEL
odoo11_addon_account_banking_mandate_sale-11.0.1.0.0.99.dev3.dist-info/top_level.txt
odoo11_addon_account_banking_mandate_sale-11.0.1.0.0.99.dev3.dist-info/RECORD
